winbundle/__init__.py
winbundle/__main__.py
winbundle/builder.py
winbundle/icon.py
winbundle/newconfig.py
winbundle/util.py
winbundle-0.1.1.post1.dist-info/LICENSE
winbundle-0.1.1.post1.dist-info/METADATA
winbundle-0.1.1.post1.dist-info/WHEEL
winbundle-0.1.1.post1.dist-info/top_level.txt
winbundle-0.1.1.post1.dist-info/RECORD
