Metadata-Version: 2.1
Name: winbundle
Version: 0.1.1.post1
Summary: A simple freezer for windows
Author-email: Alex Walters <alex.walters@gmail.com>
License: MIT
Project-URL: Source, https://github.com/tritium21/winbundle
Requires-Python: >=3.11
License-File: LICENSE
Requires-Dist: distlib
Requires-Dist: questionary
Requires-Dist: toml
Requires-Dist: pywin32-ctypes
Requires-Dist: construct
